{
  "studyGroupList": [
    {
      "id": 2,
      "name": "test",
      "coordinates": {
        "x": 0.0,
        "y": 0.0
      },
      "creationDate": "2024-03-12",
      "studentsCount": 100,
      "averageMark": 100,
      "formOfEducation": "FULL_TIME_EDUCATION",
      "semesterEnum": "EIGHTH",
      "groupAdmin": {
        "name": "admin",
        "weight": 100.0,
        "passportID": "1231231"
      }
    },
    {
      "id": 3,
      "name": "023",
      "coordinates": {
        "x": 21.0,
        "y": 32.0
      },
      "creationDate": "2024-03-12",
      "studentsCount": 1,
      "averageMark": 4,
      "formOfEducation": "FULL_TIME_EDUCATION",
      "semesterEnum": "EIGHTH",
      "groupAdmin": {
        "name": "123",
        "weight": 23.0,
        "passportID": "1231233"
      }
    },

    {
      "id": 5,
      "name": "023",
      "coordinates": {
        "x": 21.0,
        "y": 32.0
      },
      "creationDate": "2024-03-12",
      "studentsCount": 44,
      "averageMark": 4,
      "formOfEducation": "FULL_TIME_EDUCATION",
      "semesterEnum": "EIGHTH",
      "groupAdmin": {
        "name": "123",
        "weight": 23.0,
        "passportID": "1231233"
      }
    },
    {
      "id": 4,
      "name": "023",
      "coordinates": {
        "x": 21.0,
        "y": 32.0
      },
      "creationDate": "2024-03-12",
      "studentsCount": 44,
      "averageMark": 4,
      "formOfEducation": "FULL_TIME_EDUCATION",
      "semesterEnum": "EIGHTH",
      "groupAdmin": {
        "name": "123",
        "weight": 23.0,
        "passportID": "1231233"
      }
    }
  ]
}